sgml2dict/__init__.py
sgml2dict/sgml2dict.py
sgml2dict-0.0.5.dist-info/METADATA
sgml2dict-0.0.5.dist-info/WHEEL
sgml2dict-0.0.5.dist-info/licenses/LICENSE
sgml2dict-0.0.5.dist-info/RECORD
