Metadata-Version: 2.1
Name: sgml2dict
Version: 0.0.5
Summary: Convert SGML text to dictionary.
Project-URL: Homepage, https://gitlab.com/dhbmarcos/sgml2dict
Author-email: "D. H. B. Marcos" <dhbmarcos@gmail.com>
License-File: LICENSE
Classifier: License :: OSI Approved :: MIT License
Classifier: Operating System :: OS Independent
Classifier: Programming Language :: Python :: 3
Requires-Python: >=3.7
